pyspkio/__init__.py
pyspkio/spkio.py
pyspkio-0.0.31.dist-info/METADATA
pyspkio-0.0.31.dist-info/WHEEL
pyspkio-0.0.31.dist-info/licenses/LICENSE
pyspkio-0.0.31.dist-info/RECORD
