Metadata-Version: 2.4
Name: pyspkio
Version: 0.0.31
Summary: Python framework to connect Spkio Server
Project-URL: Homepage, https://github.com/spkio/pyspkio
Project-URL: Bug Tracker, https://github.com/spkyo/pyspkio/issues
Author-email: Spkio <spkio@proton.me>
License-File: LICENSE
Classifier: License :: OSI Approved :: MIT License
Classifier: Operating System :: OS Independent
Classifier: Programming Language :: Python :: 3
Requires-Python: >=3.8
